{
  "seed": 242,
  "total_count": 2,
  "collision_count": 0,
  "anomaly_count": 2,
  "low_fuel_count": 0,
  "max_danger_level": 0.7385964048415673,
  "has_danger": true,
  "events": [
    {
      "type": "anomaly",
      "type_ru": "аномалия",
      "time": 27.5,
      "severity": "HIGH",
      "value": 0.7385964048415673,
      "description": "Аномалия телеметрии, уровень 73.9%"
    },
    {
      "type": "anomaly",
      "type_ru": "аномалия",
      "time": 46.0,
      "severity": "HIGH",
      "value": 0.7335164963344994,
      "description": "Аномалия телеметрии, уровень 73.4%"
    }
  ]
}